snips_skill/__init__.py
snips_skill/__main__.py
snips_skill/dialogue.py
snips_skill/exceptions.py
snips_skill/expr.py
snips_skill/i18n.py
snips_skill/intent.py
snips_skill/log.py
snips_skill/mqtt.py
snips_skill/multi_room.py
snips_skill/parsetab.py
snips_skill/recorder.py
snips_skill/skill.py
snips_skill/snips.py
snips_skill/state.py
snips_skill/tasks.py
snips_skill/test_expr.py
snips_skill/test_schema.py
snips_skill/test_tasks.py
snips_skill/locale/snips_skill.pot
snips_skill/locale/de/LC_MESSAGES/snips_skill.mo
snips_skill/locale/de/LC_MESSAGES/snips_skill.po
snips_skill-0.1.30.dist-info/licenses/LICENSE.txt
snips_skill-0.1.30.dist-info/METADATA
snips_skill-0.1.30.dist-info/WHEEL
snips_skill-0.1.30.dist-info/entry_points.txt
snips_skill-0.1.30.dist-info/top_level.txt
snips_skill-0.1.30.dist-info/RECORD
