Metadata-Version: 2.4
Name: snips-skill
Version: 0.1.30
Summary: Boilerplate for Snips skills in Python3
Author: dnknth
License-Expression: MIT
Project-URL: Homepage, https://github.com/dnknth/snips-skill
Classifier: Operating System :: OS Independent
Classifier: Development Status :: 3 - Alpha
Classifier: Intended Audience :: Developers
Classifier: Topic :: Software Development :: Libraries
Requires-Python: >=3.10
License-File: LICENSE.txt
Requires-Dist: basecmd
Requires-Dist: croniter
Requires-Dist: paho-mqtt==1.4.*
Requires-Dist: ply==3.*
Requires-Dist: pydantic
Requires-Dist: toml
Dynamic: license-file
